{
  "emojis": [
    {
      "name": ":grinning:",
      "category": "people",
      "content": "&#128512;"
    },
    {
      "name": ":smiley:",
      "category": "people",
      "content": "&#128515;"
    },
    {
      "name": ":smile:",
      "category": "people",
      "content": "&#128516;"
    },
    {
      "name": ":grin:",
      "category": "people",
      "content": "&#128513;"
    },
    {
      "name": ":laughing::satisfied:",
      "category": "people",
      "content": "&#128518;"
    },
    {
      "name": ":sweat_smile:",
      "category": "people",
      "content": "&#128517;"
    },
    {
      "name": ":joy:",
      "category": "people",
      "content": "&#128518;"
    },
    {
      "name": ":rofl::rolling_on_the_floor_laughing:",
      "category": "people",
      "content": "&#129315;"
    },
    {
      "name": ":relaxed::blush:",
      "category": "people",
      "content": "&#128522;"
    },
    {
      "name": ":yum:",
      "category": "people",
      "content": "&#128523;"
    },
    {
      "name": ":innocent:",
      "category": "people",
      "content": "&#128519;"
    },
    {
      "name": ":slight_smile::slight_smiling_face:",
      "category": "people",
      "content": "&#128578;"
    },
    {
      "name": ":upside_down::upside_down_face:",
      "category": "people",
      "content": "&#128579;"
    },
    {
      "name": ":wink:",
      "category": "people",
      "content": "&#128521;"
    },
    {
      "name": ":relieved:",
      "category": "people",
      "content": "&#128524;"
    },
    {
      "name": ":heart_eyes:",
      "category": "people",
      "content": "&#128525;"
    },
    {
      "name": ":smiling_face_with_3_hearts:",
      "category": "people",
      "content": "&#129392;"
    },
    {
      "name": ":kissing_heart:",
      "category": "people",
      "content": "&#128536;"
    },
    {
      "name": ":kissing:",
      "category": "people",
      "content": "&#128535;"
    },
    {
      "name": ":kissing_smiling_eyes:",
      "category": "people",
      "content": "&#128537;"
    },
    {
      "name": ":kissing_closed_eyes:",
      "category": "people",
      "content": "&#128538;"
    }
  ]
}
